dokuwiki.py
dokuwiki-1.3.3.dist-info/LICENSE
dokuwiki-1.3.3.dist-info/METADATA
dokuwiki-1.3.3.dist-info/WHEEL
dokuwiki-1.3.3.dist-info/top_level.txt
dokuwiki-1.3.3.dist-info/RECORD
