Metadata-Version: 2.1
Name: dokuwiki
Version: 1.3.3
Summary: Manage DokuWiki via XML-RPC API.
Home-page: http://python-dokuwiki.readthedocs.org/en/latest/
Download-URL: https://github.com/fmenabe/python-dokuwiki
Author: François Ménabé
Author-email: francois.menabe@gmail.com
License: MIT License
Keywords: xmlrpc,dokuwiki
Platform: UNKNOWN
Classifier: Development Status :: 5 - Production/Stable
Classifier: Programming Language :: Python
Classifier: Programming Language :: Python :: 2.7
Classifier: Programming Language :: Python :: 3
Classifier: Intended Audience :: Developers
Classifier: License :: OSI Approved :: MIT License
License-File: LICENSE
